NebulaPy/__init__.py
NebulaPy/version.py
NebulaPy/data/CMFGEN.tar.xz
NebulaPy/data/Chianti.tar.xz
NebulaPy/data/PoWR.tar.xz
NebulaPy/data/__init__.py
NebulaPy/scripts/__init__.py
NebulaPy/scripts/install_silo.py
NebulaPy/scripts/install_silo.sh
NebulaPy/src/Chianti.py
NebulaPy/src/ChiantiMultiProc.py
NebulaPy/src/Cooling.py
NebulaPy/src/Database.py
NebulaPy/src/EmissionMeasure.py
NebulaPy/src/LineEmission.py
NebulaPy/src/PION.py
NebulaPy/src/SED.py
NebulaPy/src/XraySpectrum.py
NebulaPy/src/__init__.py
NebulaPy/tools/__init__.py
NebulaPy/tools/constants.py
NebulaPy/tools/util.py
NebulaPy-1.0.2b0.dist-info/METADATA
NebulaPy-1.0.2b0.dist-info/WHEEL
NebulaPy-1.0.2b0.dist-info/entry_points.txt
NebulaPy-1.0.2b0.dist-info/top_level.txt
NebulaPy-1.0.2b0.dist-info/RECORD
