Metadata-Version: 2.1
Name: NebulaPy
Version: 1.0.2b0
Summary: UNKNOWN
Home-page: UNKNOWN
Author: Arun Mathew
Author-email: arun@cp.dias.ie
License: UNKNOWN
Platform: UNKNOWN
Classifier: Development Status :: 4 - Beta
Classifier: Intended Audience :: Science/Research
Classifier: Intended Audience :: End Users/Desktop
Classifier: License :: OSI Approved :: MIT License
Classifier: Operating System :: POSIX :: Linux
Classifier: Programming Language :: Python :: 3
Classifier: Topic :: Scientific/Engineering :: Astronomy
Classifier: Topic :: Scientific/Engineering :: Physics
Requires-Dist: numpy
Requires-Dist: scipy
Requires-Dist: requests
Requires-Dist: matplotlib
Requires-Dist: ipyparallel
Requires-Dist: ChiantiPy
Requires-Dist: pypion
Requires-Dist: pandas
Requires-Dist: h5py
Requires-Dist: astropy
